{
  "no_train": true,
  "args_problems": null,
  "problem": "problem_4_aircraft_rand_17",
  "timeout": 7200.0,
  "optimiser": "trpo",
  "model": "actprop",
  "model_opts": {
    "num_layers": "3",
    "hidden_size": "16"
  },
  "all_args": [
    "--no-train",
    "--resume-from",
    "./experiment-results/experiments.ex_wargame_trial2-experiments.actprop_3l-2019-08-03T10:54:34.373401/P[domain,problem_4_aircraft_rand_1,problem_4_airc...]-S[0.01,128,lm-cut]-O[trpo]-M[actprop]-MO[num_layers=3,hidden_size=16,dropout=0.25]-T[7200]-01198928-3ecc41d/snapshots/snapshot_3_0.880000.pkl",
    "-e",
    "./experiment-results/experiments.ex_wargame_trial2-experiments.actprop_3l-2019-08-03T10:54:34.373401",
    "--supervised",
    "-O",
    "num_layers=3,hidden_size=16",
    "--det-eval",
    "--no-use-lm-cuts",
    "-R",
    "30",
    "-m",
    "actprop",
    "-L",
    "300",
    "-t",
    "7200",
    "--supervised-lr",
    "0.01",
    "--supervised-bs",
    "128",
    "--supervised-teacher-heur",
    "lm-cut",
    "../problems/ippc08/domains/wargame/domain.pddl",
    "../problems/ippc08/domains/wargame/problem_4_aircraft_rand_17.pddl"
  ],
  "elapsed_opt_time": null,
  "elapsed_opt_iters": null,
  "trial_paths": [
    [
      "(strike-long-range b1 b2 r1 r2)",
      "(strike-long-range b1 b2 r2 r3)",
      "(strike-long-range b2 b3 r2 r3)",
      "(strike-long-range b2 b3 r3 r4)",
      "(strike-long-range b2 b3 r4 r1)",
      "GOAL! :D"
    ],
    [
      "(strike-long-range b1 b2 r1 r2)",
      "(strike-long-range b2 b3 r1 r2)",
      "(strike-long-range b3 b4 r1 r2)",
      "(strike-long-range b3 b4 r2 r3)",
      "(strike-long-range b4 b1 r2 r3)",
      "(strike-long-range b4 b1 r3 r4)",
      "(strike-long-range b4 b1 r4 r1)",
      "GOAL! :D"
    ],
    [
      "(strike-long-range b1 b2 r1 r2)",
      "(strike-long-range b2 b3 r1 r2)",
      "(strike-long-range b3 b4 r1 r2)",
      "(strike-long-range b3 b4 r2 r3)",
      "(strike-long-range b3 b4 r3 r4)",
      "(strike-long-range b3 b4 r4 r1)",
      "GOAL! :D"
    ],
    [
      "(strike-long-range b1 b2 r1 r2)",
      "(strike-long-range b2 b3 r1 r2)",
      "(strike-long-range b2 b3 r2 r3)",
      "(strike-long-range b3 b4 r2 r3)",
      "(strike-long-range b4 b1 r2 r3)",
      "FAIL! D:"
    ],
    [
      "(strike-long-range b1 b2 r1 r2)",
      "(strike-long-range b1 b2 r2 r3)",
      "(strike-long-range b2 b3 r2 r3)",
      "(strike-long-range b3 b4 r2 r3)",
      "(strike-long-range b4 b1 r2 r3)",
      "FAIL! D:"
    ],
    [
      "(strike-long-range b1 b2 r1 r2)",
      "(strike-long-range b1 b2 r2 r3)",
      "(strike-long-range b2 b3 r2 r3)",
      "(strike-long-range b3 b4 r2 r3)",
      "(strike-long-range b3 b4 r3 r4)",
      "(strike-long-range b3 b4 r4 r1)",
      "(strike-long-range b4 b1 r4 r1)",
      "GOAL! :D"
    ],
    [
      "(strike-long-range b1 b2 r1 r2)",
      "(strike-long-range b2 b3 r1 r2)",
      "(strike-long-range b3 b4 r1 r2)",
      "(strike-long-range b3 b4 r2 r3)",
      "(strike-long-range b4 b1 r2 r3)",
      "(strike-long-range b4 b1 r3 r4)",
      "(strike-long-range b4 b1 r4 r1)",
      "GOAL! :D"
    ],
    [
      "(strike-long-range b1 b2 r1 r2)",
      "(strike-long-range b2 b3 r1 r2)",
      "(strike-long-range b2 b3 r2 r3)",
      "(strike-long-range b3 b4 r2 r3)",
      "(strike-long-range b4 b1 r2 r3)",
      "(strike-long-range b4 b1 r3 r4)",
      "(strike-long-range b4 b1 r4 r1)",
      "FAIL! D:"
    ],
    [
      "(strike-long-range b1 b2 r1 r2)",
      "(strike-long-range b1 b2 r2 r3)",
      "(strike-long-range b2 b3 r2 r3)",
      "(strike-long-range b3 b4 r2 r3)",
      "(strike-long-range b4 b1 r2 r3)",
      "(strike-long-range b4 b1 r3 r4)",
      "(strike-long-range b4 b1 r4 r1)",
      "FAIL! D:"
    ],
    [
      "(strike-long-range b1 b2 r1 r2)",
      "(strike-long-range b2 b3 r1 r2)",
      "(strike-long-range b3 b4 r1 r2)",
      "(strike-long-range b4 b1 r1 r2)",
      "FAIL! D:"
    ],
    [
      "(strike-long-range b1 b2 r1 r2)",
      "(strike-long-range b2 b3 r1 r2)",
      "(strike-long-range b2 b3 r2 r3)",
      "(strike-long-range b2 b3 r3 r4)",
      "(strike-long-range b2 b3 r4 r1)",
      "(strike-long-range b3 b4 r4 r1)",
      "(strike-long-range b4 b1 r4 r1)",
      "FAIL! D:"
    ],
    [
      "(strike-long-range b1 b2 r1 r2)",
      "(strike-long-range b1 b2 r2 r3)",
      "(strike-long-range b2 b3 r2 r3)",
      "(strike-long-range b2 b3 r3 r4)",
      "(strike-long-range b3 b4 r3 r4)",
      "(strike-long-range b4 b1 r3 r4)",
      "(strike-long-range b4 b1 r4 r1)",
      "GOAL! :D"
    ],
    [
      "(strike-long-range b1 b2 r1 r2)",
      "(strike-long-range b1 b2 r2 r3)",
      "(strike-long-range b1 b2 r3 r4)",
      "(strike-long-range b2 b3 r3 r4)",
      "(strike-long-range b2 b3 r4 r1)",
      "(strike-long-range b3 b4 r4 r1)",
      "(strike-long-range b4 b1 r4 r1)",
      "GOAL! :D"
    ],
    [
      "(strike-long-range b1 b2 r1 r2)",
      "(strike-long-range b2 b3 r1 r2)",
      "(strike-long-range b3 b4 r1 r2)",
      "(strike-long-range b3 b4 r2 r3)",
      "(strike-long-range b3 b4 r3 r4)",
      "(strike-long-range b4 b1 r3 r4)",
      "(strike-long-range b4 b1 r4 r1)",
      "GOAL! :D"
    ],
    [
      "(strike-long-range b1 b2 r1 r2)",
      "(strike-long-range b2 b3 r1 r2)",
      "(strike-long-range b2 b3 r2 r3)",
      "(strike-long-range b2 b3 r3 r4)",
      "(strike-long-range b3 b4 r3 r4)",
      "(strike-long-range b3 b4 r4 r1)",
      "GOAL! :D"
    ],
    [
      "(strike-long-range b1 b2 r1 r2)",
      "(strike-long-range b2 b3 r1 r2)",
      "(strike-long-range b2 b3 r2 r3)",
      "(strike-long-range b3 b4 r2 r3)",
      "(strike-long-range b3 b4 r3 r4)",
      "(strike-long-range b3 b4 r4 r1)",
      "GOAL! :D"
    ],
    [
      "(strike-long-range b1 b2 r1 r2)",
      "(strike-long-range b2 b3 r1 r2)",
      "(strike-long-range b3 b4 r1 r2)",
      "(strike-long-range b3 b4 r2 r3)",
      "(strike-long-range b3 b4 r3 r4)",
      "(strike-long-range b4 b1 r3 r4)",
      "(strike-long-range b4 b1 r4 r1)",
      "GOAL! :D"
    ],
    [
      "(strike-long-range b1 b2 r1 r2)",
      "(strike-long-range b2 b3 r1 r2)",
      "(strike-long-range b2 b3 r2 r3)",
      "(strike-long-range b3 b4 r2 r3)",
      "(strike-long-range b3 b4 r3 r4)",
      "(strike-long-range b4 b1 r3 r4)",
      "(strike-long-range b4 b1 r4 r1)",
      "FAIL! D:"
    ],
    [
      "(strike-long-range b1 b2 r1 r2)",
      "(strike-long-range b2 b3 r1 r2)",
      "(strike-long-range b3 b4 r1 r2)",
      "(strike-long-range b4 b1 r1 r2)",
      "(strike-long-range b4 b1 r2 r3)",
      "FAIL! D:"
    ],
    [
      "(strike-long-range b1 b2 r1 r2)",
      "(strike-long-range b1 b2 r2 r3)",
      "(strike-long-range b2 b3 r2 r3)",
      "(strike-long-range b3 b4 r2 r3)",
      "(strike-long-range b4 b1 r2 r3)",
      "(strike-long-range b4 b1 r3 r4)",
      "(strike-long-range b4 b1 r4 r1)",
      "GOAL! :D"
    ],
    [
      "(strike-long-range b1 b2 r1 r2)",
      "(strike-long-range b1 b2 r2 r3)",
      "(strike-long-range b2 b3 r2 r3)",
      "(strike-long-range b2 b3 r3 r4)",
      "(strike-long-range b3 b4 r3 r4)",
      "(strike-long-range b4 b1 r3 r4)",
      "(strike-long-range b4 b1 r4 r1)",
      "GOAL! :D"
    ],
    [
      "(strike-long-range b1 b2 r1 r2)",
      "(strike-long-range b2 b3 r1 r2)",
      "(strike-long-range b3 b4 r1 r2)",
      "(strike-long-range b3 b4 r2 r3)",
      "(strike-long-range b4 b1 r2 r3)",
      "(strike-long-range b4 b1 r3 r4)",
      "FAIL! D:"
    ],
    [
      "(strike-long-range b1 b2 r1 r2)",
      "(strike-long-range b1 b2 r2 r3)",
      "(strike-long-range b2 b3 r2 r3)",
      "(strike-long-range b2 b3 r3 r4)",
      "(strike-long-range b3 b4 r3 r4)",
      "(strike-long-range b4 b1 r3 r4)",
      "FAIL! D:"
    ],
    [
      "(strike-long-range b1 b2 r1 r2)",
      "(strike-long-range b2 b3 r1 r2)",
      "(strike-long-range b2 b3 r2 r3)",
      "(strike-long-range b2 b3 r3 r4)",
      "(strike-long-range b2 b3 r4 r1)",
      "GOAL! :D"
    ],
    [
      "(strike-long-range b1 b2 r1 r2)",
      "(strike-long-range b1 b2 r2 r3)",
      "(strike-long-range b1 b2 r3 r4)",
      "(strike-long-range b2 b3 r3 r4)",
      "(strike-long-range b3 b4 r3 r4)",
      "(strike-long-range b4 b1 r3 r4)",
      "FAIL! D:"
    ],
    [
      "(strike-long-range b1 b2 r1 r2)",
      "(strike-long-range b2 b3 r1 r2)",
      "(strike-long-range b3 b4 r1 r2)",
      "(strike-long-range b4 b1 r1 r2)",
      "(strike-long-range b4 b1 r2 r3)",
      "(strike-long-range b4 b1 r3 r4)",
      "(strike-long-range b4 b1 r4 r1)",
      "FAIL! D:"
    ],
    [
      "(strike-long-range b1 b2 r1 r2)",
      "(strike-long-range b2 b3 r1 r2)",
      "(strike-long-range b2 b3 r2 r3)",
      "(strike-long-range b3 b4 r2 r3)",
      "(strike-long-range b3 b4 r3 r4)",
      "(strike-long-range b4 b1 r3 r4)",
      "(strike-long-range b4 b1 r4 r1)",
      "FAIL! D:"
    ],
    [
      "(strike-long-range b1 b2 r1 r2)",
      "(strike-long-range b1 b2 r2 r3)",
      "(strike-long-range b2 b3 r2 r3)",
      "(strike-long-range b3 b4 r2 r3)",
      "(strike-long-range b3 b4 r3 r4)",
      "(strike-long-range b4 b1 r3 r4)",
      "FAIL! D:"
    ],
    [
      "(strike-long-range b1 b2 r1 r2)",
      "(strike-long-range b2 b3 r1 r2)",
      "(strike-long-range b3 b4 r1 r2)",
      "(strike-long-range b3 b4 r2 r3)",
      "(strike-long-range b3 b4 r3 r4)",
      "(strike-long-range b4 b1 r3 r4)",
      "(strike-long-range b4 b1 r4 r1)",
      "GOAL! :D"
    ],
    [
      "(strike-long-range b1 b2 r1 r2)",
      "(strike-long-range b2 b3 r1 r2)",
      "(strike-long-range b2 b3 r2 r3)",
      "(strike-long-range b3 b4 r2 r3)",
      "(strike-long-range b4 b1 r2 r3)",
      "(strike-long-range b4 b1 r3 r4)",
      "(strike-long-range b4 b1 r4 r1)",
      "GOAL! :D"
    ]
  ],
  "turn_limit": 300,
  "trials": 30,
  "all_goal_reached": [
    true,
    true,
    true,
    false,
    false,
    true,
    true,
    false,
    false,
    false,
    false,
    true,
    true,
    true,
    true,
    true,
    true,
    false,
    false,
    true,
    true,
    false,
    false,
    true,
    false,
    false,
    false,
    false,
    true,
    true
  ],
  "all_exec_times": [
    0.3659021854400635,
    0.07389402389526367,
    0.06349849700927734,
    0.054318904876708984,
    0.05451059341430664,
    0.0711662769317627,
    0.07283949851989746,
    0.07223749160766602,
    0.07418298721313477,
    0.04634356498718262,
    0.07263422012329102,
    0.07292532920837402,
    0.07207512855529785,
    0.0725853443145752,
    0.06312799453735352,
    0.06262850761413574,
    0.07204961776733398,
    0.07409214973449707,
    0.055370330810546875,
    0.0725858211517334,
    0.07323408126831055,
    0.06307554244995117,
    0.06422209739685059,
    0.055461883544921875,
    0.06310272216796875,
    0.07300281524658203,
    0.07311201095581055,
    0.06390953063964844,
    0.07340359687805176,
    0.07231330871582031
  ],
  "all_costs": [
    5,
    7,
    6,
    5,
    5,
    7,
    7,
    7,
    7,
    4,
    7,
    7,
    7,
    7,
    6,
    6,
    7,
    7,
    5,
    7,
    7,
    6,
    6,
    5,
    6,
    7,
    7,
    6,
    7,
    7
  ]
}